{"name":"MQ","slug":"MQ","count":1,"postlist":[{"title":"消息队列","uid":"a238c8f44f70d50de3377d42da7a86a2","slug":"消息队列","date":"2021-01-22T08:57:26.000Z","updated":"2021-11-30T09:00:19.903Z","comments":true,"path":"api/articles/消息队列.json","keywords":"node.js blogs IT 互联网 服务端 游戏 mysql redis","cover":[],"text":"消息队列是分布式应用间交换信息的重要组件，消息队列可驻留在内存或磁盘上, 队列可以存储消息直到它们被应用程序读走。 通过消息队列，应用程序可以在不知道彼此位置的情况下独立处理消息，或者在处理消息前不需要等待接收此消息。 所以消息队列可以解决应用解耦、异步消息、流量削锋等问题，是实...","link":"","photos":[],"count_time":{"symbolsCount":858,"symbolsTime":"1 mins."},"categories":[{"name":"IT笔记","slug":"IT笔记","count":21,"path":"api/categories/IT笔记.json"}],"tags":[{"name":"MQ","slug":"MQ","count":1,"path":"api/tags/MQ.json"}],"author":{"name":"Fly","slug":"blog-author","avatar":"https://img-blog.csdnimg.cn/20210313122054101.png","link":"/","description":"一个在夏天会被芒果砸到的城市靠写代码为生的前职业电竞选手","socials":{"github":"","twitter":"","stackoverflow":"","wechat":"","qq":"","weibo":"","zhihu":"","csdn":"","juejin":"","customs":{}}}}]}